geometry/__init__.py
geometry/kubus.py
geometry/lingkaran.py
geometry/persegi.py
pelatihan_bmkg-0.0.4.dist-info/LICENSE.txt
pelatihan_bmkg-0.0.4.dist-info/METADATA
pelatihan_bmkg-0.0.4.dist-info/WHEEL
pelatihan_bmkg-0.0.4.dist-info/top_level.txt
pelatihan_bmkg-0.0.4.dist-info/RECORD
